gcln/__init__.py
gcln/cfg_file.py
gcln/exceptions.py
gcln/helpers.py
gcln/main.py
gcln/main_context.py
gcln/records.py
gcln/srv_connector.py
gcln2/__init__.py
gcln2/db.py
gcln2/exceptions.py
gcln2/helpers.py
gcln2/main.py
gcln2/schema.py
gcln2/sync.py
gcln2/yaml_loader.py
gitcoll-0.0.24.dist-info/LICENSE
gitcoll-0.0.24.dist-info/METADATA
gitcoll-0.0.24.dist-info/WHEEL
gitcoll-0.0.24.dist-info/entry_points.txt
gitcoll-0.0.24.dist-info/top_level.txt
gitcoll-0.0.24.dist-info/RECORD
